Metadata-Version: 2.1
Name: sopel-modules.trakt
Version: 0.1.0
Summary: A sopel plugin that returns the user's last play on trakt
Home-page: https://github.com/shanedabes/sopel-trakt
Author: Shane Donohoe
Author-email: shane@donohoe.cc
License: Eiffel Forum License, version 2
Platform: UNKNOWN
Requires-Dist: sopel (<7,>=6.0)
